Topsis_IshanGoyal_102203961/__init__.py
Topsis_IshanGoyal_102203961/__main__.py
Topsis_IshanGoyal_102203961/topsis.py
Topsis_IshanGoyal_102203961-1.0.15.dist-info/METADATA
Topsis_IshanGoyal_102203961-1.0.15.dist-info/WHEEL
Topsis_IshanGoyal_102203961-1.0.15.dist-info/entry_points.txt
Topsis_IshanGoyal_102203961-1.0.15.dist-info/top_level.txt
Topsis_IshanGoyal_102203961-1.0.15.dist-info/RECORD
