Metadata-Version: 2.1
Name: Topsis_IshanGoyal_102203961
Version: 1.0.15
Summary: A python package for implementing topsis
Home-page: https://github.com/goyalishan/Topsis_102203961
Author: Ishan Goyal
Author-email: igoyal_be22@thapar.com
Classifier: Programming Language :: Python :: 3
Classifier: License :: OSI Approved :: MIT License
Classifier: Operating System :: OS Independent
Requires-Dist: pandas
Requires-Dist: numpy
